confspec/__init__.py
confspec/helpers.py
confspec/interpolate.py
confspec/loader.py
confspec/py.typed
confspec/parsers/__init__.py
confspec/parsers/abc.py
confspec/parsers/json.py
confspec/parsers/toml.py
confspec/parsers/yaml.py
confspec-0.0.5.dist-info/licenses/LICENSE
confspec-0.0.5.dist-info/WHEEL
confspec-0.0.5.dist-info/METADATA
confspec-0.0.5.dist-info/RECORD
