Metadata-Version: 2.4
Name: confspec
Version: 0.0.5
Summary: Parse YAML, JSON, and TOML into Python objects with smart environment variable interpolation.
Keywords: configuration,config,settings,environment,env,yaml,toml,json,schema,config-file,environment-variables,structured-config,config-loader,environment-substitution
Author-email: tandemdude <tandemdude1@gmail.com>
Requires-Python: >=3.11.0,<3.15
Classifier: Development Status :: 3 - Alpha
Classifier: License :: OSI Approved :: MIT License
Classifier: Intended Audience :: Developers
Classifier: Natural Language :: English
Classifier: Topic :: Software Development :: Libraries :: Python Modules
Classifier: Programming Language :: Python :: 3.11
Classifier: Programming Language :: Python :: 3.12
Classifier: Programming Language :: Python :: 3.13
Classifier: Programming Language :: Python :: Implementation :: CPython
Classifier: Programming Language :: Python :: 3 :: Only
Classifier: Topic :: Software Development :: Libraries
Classifier: Topic :: Software Development :: Libraries :: Python Modules
Classifier: Typing :: Typed
License-File: LICENSE
Project-URL: Homepage, https://github.com/tandemdude/confspec
Project-URL: Repository, https://github.com/tandemdude/confspec
